[
 {
  "Description": "Detected a Generic API Key, potentially exposing access to various services and sensitive operations.",
  "StartLine": 7,
  "EndLine": 7,
  "StartColumn": 11,
  "EndColumn": 47,
  "Match": "MCP_API_KEY\": \"sk_manus_12345_secret\"",
  "Secret": "sk_manus_12345_secret",
  "File": ".cursor/mcp.json",
  "SymlinkFile": "",
  "Commit": "de1f3b28b735834599bcd79d3329498c28975036",
  "Entropy": 3.8442328,
  "Author": "Vinícius Uchita",
  "Email": "viniciusuchita@gmail.com",
  "Date": "2025-05-20T06:58:50Z",
  "Message": "Agents installed",
  "Tags": [],
  "RuleID": "generic-api-key",
  "Fingerprint": "de1f3b28b735834599bcd79d3329498c28975036:.cursor/mcp.json:generic-api-key:7"
 },
 {
  "Description": "Detected a Generic API Key, potentially exposing access to various services and sensitive operations.",
  "StartLine": 79,
  "EndLine": 79,
  "StartColumn": 20,
  "EndColumn": 53,
  "Match": "MCP_API_KEY=sk_manus_12345_secret ",
  "Secret": "sk_manus_12345_secret",
  "File": "manus_mcp_setup.json",
  "SymlinkFile": "",
  "Commit": "de1f3b28b735834599bcd79d3329498c28975036",
  "Entropy": 3.8442328,
  "Author": "Vinícius Uchita",
  "Email": "viniciusuchita@gmail.com",
  "Date": "2025-05-20T06:58:50Z",
  "Message": "Agents installed",
  "Tags": [],
  "RuleID": "generic-api-key",
  "Fingerprint": "de1f3b28b735834599bcd79d3329498c28975036:manus_mcp_setup.json:generic-api-key:79"
 },
 {
  "Description": "Detected a Generic API Key, potentially exposing access to various services and sensitive operations.",
  "StartLine": 98,
  "EndLine": 98,
  "StartColumn": 17,
  "EndColumn": 53,
  "Match": "MCP_API_KEY\": \"sk_manus_12345_secret\"",
  "Secret": "sk_manus_12345_secret",
  "File": "manus_mcp_setup.json",
  "SymlinkFile": "",
  "Commit": "de1f3b28b735834599bcd79d3329498c28975036",
  "Entropy": 3.8442328,
  "Author": "Vinícius Uchita",
  "Email": "viniciusuchita@gmail.com",
  "Date": "2025-05-20T06:58:50Z",
  "Message": "Agents installed",
  "Tags": [],
  "RuleID": "generic-api-key",
  "Fingerprint": "de1f3b28b735834599bcd79d3329498c28975036:manus_mcp_setup.json:generic-api-key:98"
 },
 {
  "Description": "Detected a Generic API Key, potentially exposing access to various services and sensitive operations.",
  "StartLine": 18,
  "EndLine": 18,
  "StartColumn": 4,
  "EndColumn": 57,
  "Match": "secret: testSecretKey12345678901234567890testSecretKey",
  "Secret": "testSecretKey12345678901234567890testSecretKey",
  "File": "src/test/resources/application-test.yml",
  "SymlinkFile": "",
  "Commit": "9f2e484688ff972c57a6a99bbb4358cdcbe053ca",
  "Entropy": 3.9690015,
  "Author": "Vinícius Uchita",
  "Email": "viniciusuchita@gmail.com",
  "Date": "2025-05-15T21:26:18Z",
  "Message": "\"first commit project fechamento_de_caixa\"",
  "Tags": [],
  "RuleID": "generic-api-key",
  "Fingerprint": "9f2e484688ff972c57a6a99bbb4358cdcbe053ca:src/test/resources/application-test.yml:generic-api-key:18"
 },
 {
  "Description": "Detected a Generic API Key, potentially exposing access to various services and sensitive operations.",
  "StartLine": 80,
  "EndLine": 80,
  "StartColumn": 17,
  "EndColumn": 70,
  "Match": "invalidToken = \"eyJhbGciOiJIUzI1NiIsInR5cCI6IkpXVCJ9.\"",
  "Secret": "eyJhbGciOiJIUzI1NiIsInR5cCI6IkpXVCJ9.",
  "File": "src/test/java/com/seucodigo/fecharcaixa/integration/SecurityIntegrationTest.java",
  "SymlinkFile": "",
  "Commit": "9f2e484688ff972c57a6a99bbb4358cdcbe053ca",
  "Entropy": 4.4251413,
  "Author": "Vinícius Uchita",
  "Email": "viniciusuchita@gmail.com",
  "Date": "2025-05-15T21:26:18Z",
  "Message": "\"first commit project fechamento_de_caixa\"",
  "Tags": [],
  "RuleID": "generic-api-key",
  "Fingerprint": "9f2e484688ff972c57a6a99bbb4358cdcbe053ca:src/test/java/com/seucodigo/fecharcaixa/integration/SecurityIntegrationTest.java:generic-api-key:80"
 },
 {
  "Description": "Detected a Generic API Key, potentially exposing access to various services and sensitive operations.",
  "StartLine": 18,
  "EndLine": 18,
  "StartColumn": 4,
  "EndColumn": 57,
  "Match": "secret: testSecretKey12345678901234567890testSecretKey",
  "Secret": "testSecretKey12345678901234567890testSecretKey",
  "File": "target/test-classes/application-test.yml",
  "SymlinkFile": "",
  "Commit": "9f2e484688ff972c57a6a99bbb4358cdcbe053ca",
  "Entropy": 3.9690015,
  "Author": "Vinícius Uchita",
  "Email": "viniciusuchita@gmail.com",
  "Date": "2025-05-15T21:26:18Z",
  "Message": "\"first commit project fechamento_de_caixa\"",
  "Tags": [],
  "RuleID": "generic-api-key",
  "Fingerprint": "9f2e484688ff972c57a6a99bbb4358cdcbe053ca:target/test-classes/application-test.yml:generic-api-key:18"
 }
]
